Metadata-Version: 2.0
Name: my-package-19CS30013
Version: 0.0.3
Summary: My package
Home-page: UNKNOWN
Author: Satwik Chappidi
Author-email: <youremail@email.com>
License: UNKNOWN
Keywords: python,first package
Platform: UNKNOWN
Classifier: Development Status :: 3 - Alpha
Classifier: Intended Audience :: Education
Classifier: Programming Language :: Python :: 2
Classifier: Programming Language :: Python :: 3
Classifier: Operating System :: MacOS :: MacOS X
Classifier: Operating System :: Microsoft :: Windows
